prc_sdk/__init__.py
prc_sdk/client.py
prc_sdk/constants.py
prc_sdk/errors.py
prc_sdk/logging.py
prc_sdk/utils.py
prc_sdk/models/__init__.py
prc_sdk/models/logs.py
prc_sdk/models/player.py
prc_sdk/models/server.py
prc_sdk-0.1.2.dist-info/LICENSE
prc_sdk-0.1.2.dist-info/METADATA
prc_sdk-0.1.2.dist-info/WHEEL
prc_sdk-0.1.2.dist-info/top_level.txt
prc_sdk-0.1.2.dist-info/RECORD
