Metadata-Version: 2.2
Name: prc_sdk
Version: 0.1.2
Summary: A Python SDK for interacting with the PRC API
Home-page: https://github.com/zenturocloud/prc-roblox-sdk-python
Author: zenturocloud
Author-email: zenturocloud <info@zenturo.cloud>
License: MIT
Project-URL: Homepage, https://github.com/zenturocloud/prc-roblox-sdk-python
Project-URL: Bug Tracker, https://github.com/zenturocloud/prc-roblox-sdk-python/issues
Keywords: prc,roblox,api,sdk
Classifier: Programming Language :: Python :: 3
Classifier: Programming Language :: Python :: 3.7
Classifier: Programming Language :: Python :: 3.8
Classifier: Programming Language :: Python :: 3.9
Classifier: Programming Language :: Python :: 3.10
Classifier: License :: OSI Approved :: MIT License
Classifier: Operating System :: OS Independent
Classifier: Intended Audience :: Developers
Classifier: Topic :: Software Development :: Libraries :: Python Modules
Requires-Python: >=3.7
License-File: LICENSE
Requires-Dist: requests>=2.25.0
Dynamic: author
Dynamic: home-page
Dynamic: requires-python
